{
  "associatedLayout": "Exploration",
  "name": "Frederick Douglass Square",
  "instances": [
    {
      "angle": 0,
      "customSize": false,
      "height": 0,
      "keepRatio": true,
      "layer": "Background",
      "name": "Background",
      "persistentUuid": "f5d0205d-4ccd-4dde-9851-5867884be3e7",
      "width": 0,
      "x": 0,
      "y": -133,
      "zOrder": 2,
      "numberProperties": [],
      "stringProperties": [],
      "initialVariables": []
    },
    {
      "angle": 91,
      "customSize": false,
      "flippedX": true,
      "height": 0,
      "keepRatio": true,
      "layer": "SceneObjects",
      "name": "TransitionObject",
      "persistentUuid": "6839d4f1-1f84-4392-996b-20f87258abb1",
      "width": 0,
      "x": 863,
      "y": 479,
      "zOrder": 3,
      "numberProperties": [],
      "stringProperties": [],
      "initialVariables": []
    },
    {
      "angle": 0,
      "customSize": true,
      "depth": 0,
      "height": 216,
      "keepRatio": true,
      "layer": "SceneObjects",
      "name": "InteractionObject",
      "persistentUuid": "142f4d95-7205-4398-8901-a41f95717096",
      "width": 128,
      "x": 704,
      "y": 432,
      "zOrder": 4,
      "numberProperties": [
        {
          "name": "animation",
          "value": 2
        }
      ],
      "stringProperties": [],
      "initialVariables": []
    },
    {
      "angle": 0,
      "customSize": false,
      "height": 0,
      "keepRatio": true,
      "layer": "SceneObjects",
      "name": "InspectionObject",
      "persistentUuid": "58c894a4-9b9a-43a5-9ccd-b70172f1adfd",
      "width": 0,
      "x": 288,
      "y": 336,
      "zOrder": 5,
      "numberProperties": [],
      "stringProperties": [],
      "initialVariables": [
        {
          "name": "targetInspection",
          "type": "string",
          "value": "FDStatueInspect"
        }
      ]
    },
    {
      "angle": 0,
      "customSize": true,
      "depth": 1,
      "height": 544,
      "keepRatio": true,
      "layer": "InspectionObjects",
      "name": "InspectionBackground",
      "persistentUuid": "eb466e03-80b7-4937-b846-7b944f38e6a0",
      "width": 960,
      "x": 1360,
      "y": 0,
      "zOrder": 6,
      "numberProperties": [],
      "stringProperties": [],
      "initialVariables": [
        {
          "name": "inspectionName",
          "type": "string",
          "value": "FDStatueInspect"
        }
      ]
    },
    {
      "angle": 0,
      "customSize": true,
      "depth": 1,
      "height": 480,
      "keepRatio": true,
      "layer": "InspectionObjects",
      "name": "InspectionImage",
      "persistentUuid": "b33eccdf-af94-46f5-a099-cc4e66d8bfec",
      "width": 353,
      "x": 1392,
      "y": 32,
      "zOrder": 7,
      "numberProperties": [],
      "stringProperties": [],
      "initialVariables": [
        {
          "name": "inspectionName",
          "type": "string",
          "value": "FDStatueInspect"
        }
      ]
    },
    {
      "angle": 0,
      "customSize": true,
      "depth": 1,
      "height": 480,
      "keepRatio": true,
      "layer": "InspectionObjects",
      "name": "InspectionText",
      "persistentUuid": "9c85efeb-2a58-43be-95a3-051a13d87154",
      "width": 480,
      "x": 1792,
      "y": 272,
      "zOrder": 8,
      "numberProperties": [],
      "stringProperties": [],
      "initialVariables": [
        {
          "name": "innerText",
          "type": "string",
          "value": "A large statue of Frederick Douglass. Several of his quotes are etched into the stone floor."
        },
        {
          "name": "inspectionName",
          "type": "string",
          "value": "FDStatueInspect"
        }
      ]
    },
    {
      "angle": 0,
      "customSize": false,
      "height": 0,
      "keepRatio": true,
      "layer": "SceneObjects",
      "name": "InspectionObject",
      "persistentUuid": "1d7473c9-131e-4d57-ab30-4668b489cff1",
      "width": 0,
      "x": 512,
      "y": 592,
      "zOrder": 9,
      "numberProperties": [],
      "stringProperties": [],
      "initialVariables": [
        {
          "name": "targetInspection",
          "type": "string",
          "value": "QuotesInspect"
        }
      ]
    },
    {
      "angle": 0,
      "customSize": false,
      "height": 0,
      "keepRatio": true,
      "layer": "InspectionObjects",
      "name": "InspectionBackground",
      "persistentUuid": "c5a29681-0ba3-4da6-bacf-8d05e838200e",
      "width": 0,
      "x": 1360,
      "y": 576,
      "zOrder": 10,
      "numberProperties": [],
      "stringProperties": [],
      "initialVariables": [
        {
          "name": "inspectionName",
          "type": "string",
          "value": "QuotesInspect"
        }
      ]
    },
    {
      "angle": 0,
      "customSize": true,
      "depth": 0,
      "height": 115,
      "keepRatio": true,
      "layer": "InspectionObjects",
      "name": "InspectionImage",
      "persistentUuid": "a0debf05-4eb5-4a20-9afa-95c28d8b7d1b",
      "width": 352,
      "x": 1392,
      "y": 608,
      "zOrder": 11,
      "numberProperties": [
        {
          "name": "animation",
          "value": 3
        }
      ],
      "stringProperties": [],
      "initialVariables": [
        {
          "name": "inspectionName",
          "type": "string",
          "value": "QuotesInspect"
        }
      ]
    },
    {
      "angle": 0,
      "customSize": true,
      "depth": 1,
      "height": 128,
      "keepRatio": true,
      "layer": "InspectionObjects",
      "name": "InspectionImage",
      "persistentUuid": "96240b94-9635-4143-b9f1-961edbf10c99",
      "width": 464,
      "x": 1392,
      "y": 736,
      "zOrder": 12,
      "numberProperties": [
        {
          "name": "animation",
          "value": 4
        }
      ],
      "stringProperties": [],
      "initialVariables": [
        {
          "name": "inspectionName",
          "type": "string",
          "value": "QuotesInspect"
        }
      ]
    },
    {
      "angle": 0,
      "customSize": true,
      "depth": 1,
      "height": 208,
      "keepRatio": true,
      "layer": "InspectionObjects",
      "name": "InspectionImage",
      "persistentUuid": "ce6487a0-9337-4922-bc77-2d1fcbbe8c2d",
      "width": 485,
      "x": 1392,
      "y": 880,
      "zOrder": 13,
      "numberProperties": [
        {
          "name": "animation",
          "value": 5
        }
      ],
      "stringProperties": [],
      "initialVariables": [
        {
          "name": "inspectionName",
          "type": "string",
          "value": "QuotesInspect"
        }
      ]
    },
    {
      "angle": 0,
      "customSize": false,
      "height": 0,
      "keepRatio": true,
      "layer": "InspectionObjects",
      "name": "InspectionObject",
      "persistentUuid": "13678e6a-8761-4af8-969f-8fdd96081fa2",
      "width": 0,
      "x": 1680,
      "y": 656,
      "zOrder": 14,
      "numberProperties": [],
      "stringProperties": [],
      "initialVariables": [
        {
          "name": "targetInspection",
          "type": "string",
          "value": "QuoteInspect1"
        }
      ]
    },
    {
      "angle": 0,
      "customSize": false,
      "height": 0,
      "keepRatio": true,
      "layer": "InspectionObjects",
      "name": "InspectionObject",
      "persistentUuid": "76e243ac-95ec-4bfe-b41f-91c6cdb80e98",
      "width": 0,
      "x": 1792,
      "y": 800,
      "zOrder": 15,
      "numberProperties": [],
      "stringProperties": [],
      "initialVariables": [
        {
          "name": "targetInspection",
          "type": "string",
          "value": "QuoteInspect2"
        }
      ]
    },
    {
      "angle": 0,
      "customSize": false,
      "height": 0,
      "keepRatio": true,
      "layer": "InspectionObjects",
      "name": "InspectionObject",
      "persistentUuid": "ebf6ef5d-e26d-477b-b52a-2169b491e50e",
      "width": 0,
      "x": 1808,
      "y": 1024,
      "zOrder": 16,
      "numberProperties": [],
      "stringProperties": [],
      "initialVariables": [
        {
          "name": "targetInspection",
          "type": "string",
          "value": "QuoteInspect3"
        }
      ]
    },
    {
      "angle": 0,
      "customSize": true,
      "depth": 1,
      "height": 480,
      "keepRatio": true,
      "layer": "InspectionObjects",
      "name": "InspectionText",
      "persistentUuid": "dd05cddc-703d-414f-9faa-ecb529a6d79c",
      "width": 384,
      "x": 1904,
      "y": 848,
      "zOrder": 17,
      "numberProperties": [],
      "stringProperties": [],
      "initialVariables": [
        {
          "name": "innerText",
          "type": "string",
          "value": "Several quotes by Frederick Douglass are etched into the stone."
        },
        {
          "name": "inspectionName",
          "type": "string",
          "value": "QuotesInspect"
        }
      ]
    },
    {
      "angle": 0,
      "customSize": false,
      "height": 0,
      "keepRatio": true,
      "layer": "InspectionObjects",
      "name": "InspectionBackground",
      "persistentUuid": "5be7591f-17aa-497f-910f-e0267dff0e1e",
      "width": 0,
      "x": 2352,
      "y": 576,
      "zOrder": 18,
      "numberProperties": [],
      "stringProperties": [],
      "initialVariables": [
        {
          "name": "inspectionName",
          "type": "string",
          "value": "QuoteInspect1"
        }
      ]
    },
    {
      "angle": 0,
      "customSize": true,
      "depth": 1,
      "height": 480,
      "keepRatio": true,
      "layer": "InspectionObjects",
      "name": "InspectionText",
      "persistentUuid": "dce5cd59-dda4-4eda-9c97-0abb17ff8826",
      "width": 896,
      "x": 2384,
      "y": 848,
      "zOrder": 19,
      "numberProperties": [],
      "stringProperties": [],
      "initialVariables": [
        {
          "name": "innerText",
          "type": "string",
          "value": "\"Once you learn to read, you will forever be free.\""
        },
        {
          "name": "inspectionName",
          "type": "string",
          "value": "QuoteInspect1"
        }
      ]
    },
    {
      "angle": 0,
      "customSize": true,
      "depth": 1,
      "height": 64,
      "keepRatio": true,
      "layer": "InspectionObjects",
      "name": "InspectionObject",
      "persistentUuid": "93da81a5-4473-4d5c-9da8-50462c462856",
      "width": 64,
      "x": 2368,
      "y": 592,
      "zOrder": 20,
      "numberProperties": [
        {
          "name": "animation",
          "value": 1
        }
      ],
      "stringProperties": [],
      "initialVariables": [
        {
          "name": "targetInspection",
          "type": "string",
          "value": "QuotesInspect"
        }
      ]
    },
    {
      "angle": 0,
      "customSize": false,
      "height": 0,
      "keepRatio": true,
      "layer": "InspectionObjects",
      "name": "InspectionBackground",
      "persistentUuid": "345a67a4-400c-4562-baa7-23ddb3cc15ad",
      "width": 0,
      "x": 3328,
      "y": 576,
      "zOrder": 18,
      "numberProperties": [],
      "stringProperties": [],
      "initialVariables": [
        {
          "name": "inspectionName",
          "type": "string",
          "value": "QuoteInspect2"
        }
      ]
    },
    {
      "angle": 0,
      "customSize": true,
      "depth": 1,
      "height": 64,
      "keepRatio": true,
      "layer": "InspectionObjects",
      "name": "InspectionObject",
      "persistentUuid": "c5808101-60af-444c-a53f-a02017daf154",
      "width": 64,
      "x": 3344,
      "y": 592,
      "zOrder": 20,
      "numberProperties": [
        {
          "name": "animation",
          "value": 1
        }
      ],
      "stringProperties": [],
      "initialVariables": [
        {
          "name": "targetInspection",
          "type": "string",
          "value": "QuotesInspect"
        }
      ]
    },
    {
      "angle": 0,
      "customSize": true,
      "depth": 1,
      "height": 480,
      "keepRatio": true,
      "layer": "InspectionObjects",
      "name": "InspectionText",
      "persistentUuid": "a97e42e3-7f15-4273-85c1-039b58ff14de",
      "width": 896,
      "x": 3360,
      "y": 848,
      "zOrder": 19,
      "numberProperties": [],
      "stringProperties": [],
      "initialVariables": [
        {
          "name": "innerText",
          "type": "string",
          "value": "\"I was born in Tuckahoe, near Hillsborough, and about twelve miles from Easton, in Talbot County, Maryland.\""
        },
        {
          "name": "inspectionName",
          "type": "string",
          "value": "QuoteInspect2"
        }
      ]
    },
    {
      "angle": 0,
      "customSize": true,
      "depth": 1,
      "height": 64,
      "keepRatio": true,
      "layer": "InspectionObjects",
      "name": "InspectionObject",
      "persistentUuid": "4237493e-c608-497c-9fae-9dd3dc30c878",
      "width": 64,
      "x": 4320,
      "y": 592,
      "zOrder": 20,
      "numberProperties": [
        {
          "name": "animation",
          "value": 1
        }
      ],
      "stringProperties": [],
      "initialVariables": [
        {
          "name": "targetInspection",
          "type": "string",
          "value": "QuotesInspect"
        }
      ]
    },
    {
      "angle": 0,
      "customSize": false,
      "height": 0,
      "keepRatio": true,
      "layer": "InspectionObjects",
      "name": "InspectionBackground",
      "persistentUuid": "139ea5f6-5733-41f2-9f3e-625a25f6de66",
      "width": 0,
      "x": 4304,
      "y": 576,
      "zOrder": 18,
      "numberProperties": [],
      "stringProperties": [],
      "initialVariables": [
        {
          "name": "inspectionName",
          "type": "string",
          "value": "QuoteInspect3"
        }
      ]
    },
    {
      "angle": 0,
      "customSize": true,
      "depth": 1,
      "height": 480,
      "keepRatio": true,
      "layer": "InspectionObjects",
      "name": "InspectionText",
      "persistentUuid": "5a1df3bd-462d-4089-9253-b5e877de4b00",
      "width": 896,
      "x": 4336,
      "y": 848,
      "zOrder": 19,
      "numberProperties": [],
      "stringProperties": [],
      "initialVariables": [
        {
          "name": "innerText",
          "type": "string",
          "value": "\"Until it shall be safe to leave the lamb in the hold of the lion, the laborer in the power of the capitalist, the poor in the hands of the rich, it will not be safe to leave a newly emancipated people completely in the power of their former masters, especially when such masters have not ceased to be such from enlightened moral convictions but by irresistible force.\""
        },
        {
          "name": "inspectionName",
          "type": "string",
          "value": "QuoteInspect3"
        }
      ]
    }
  ],
  "editionSettings": {
    "grid": true,
    "gridType": "rectangular",
    "gridWidth": 16,
    "gridHeight": 16,
    "gridDepth": 32,
    "gridOffsetX": 0,
    "gridOffsetY": 0,
    "gridOffsetZ": 0,
    "gridColor": 10401023,
    "gridAlpha": 0.8,
    "snap": true,
    "zoomFactor": 0.4194339782759098,
    "windowMask": false,
    "selectedLayer": "InspectionObjects"
  }
}